{
  "programs": [
    {
      "code": "PLSC-BA",
      "name": "Political Science (BA)",
      "type": "major",
      "department": "PLSC",
      "total_credits": 33,
      "unique_credits_required": 21,
      "double_dip_policy": "CAS_DEFAULT",
      "core_waivers": [
        "Societal/Cultural"
      ],
      "notes": [
        "At least 17 credit hours of PLSC courses must be completed at Loyola.",
        "PLSC 395 Honors Seminar does not count toward major.",
        "PLSC 216 counts as elective only (also fulfills core quantitative).",
        "PLSC 396 Directed Readings counts as elective only.",
        "Only 3 credits of PLSC 370 may count toward major."
      ],
      "categories": [
        {
          "name": "Foundation Courses",
          "description": "Select three of the following four",
          "slots": 3,
          "credits_per_slot": 3,
          "eligible_courses": [
            "PLSC 100",
            "PLSC 101",
            "PLSC 102",
            "PLSC 103"
          ],
          "notes": "If taking PLSC 100, 101, or 102 as the three, PLSC 103 can count as elective"
        },
        {
          "name": "American Politics Subfield",
          "slots": 1,
          "credits_per_slot": 3,
          "eligible_courses": [
            "PLSC 202",
            "PLSC 203",
            "PLSC 208",
            "PLSC 215",
            "PLSC 218",
            "PLSC 236",
            "PLSC 238",
            "PLSC 251",
            "PLSC 300A",
            "PLSC 318",
            "PLSC 319",
            "PLSC 320",
            "PLSC 321",
            "PLSC 322",
            "PLSC 323",
            "PLSC 324",
            "PLSC 326",
            "PLSC 327",
            "PLSC 328",
            "PLSC 329",
            "PLSC 332",
            "PLSC 334",
            "PLSC 335",
            "PLSC 357",
            "PLSC 372",
            "PLSC 376",
            "PLSC 377",
            "PLSC 378",
            "PLSC 379",
            "PLSC 380",
            "PLSC 381",
            "PLSC 384",
            "PLSC 385",
            "PLSC 386",
            "PLSC 387",
            "PLSC 389",
            "PLSC 390",
            "PLSC 391",
            "PLSC 392",
            "PLSC 393",
            "PLSC 398"
          ]
        },
        {
          "name": "Political Theory Subfield",
          "slots": 1,
          "credits_per_slot": 3,
          "eligible_courses": [
            "PLSC 300B",
            "PLSC 301",
            "PLSC 302",
            "PLSC 303",
            "PLSC 304",
            "PLSC 306",
            "PLSC 307",
            "PLSC 308",
            "PLSC 309",
            "PLSC 310B",
            "PLSC 311",
            "PLSC 312",
            "PLSC 313",
            "PLSC 314",
            "PLSC 330",
            "PLSC 331",
            "PLSC 339",
            "PLSC 371",
            "PLSC 373",
            "PLSC 388"
          ]
        },
        {
          "name": "Comparative Politics Subfield",
          "slots": 1,
          "credits_per_slot": 3,
          "eligible_courses": [
            "PLSC 232",
            "PLSC 300C",
            "PLSC 336",
            "PLSC 337",
            "PLSC 339",
            "PLSC 342",
            "PLSC 343",
            "PLSC 344",
            "PLSC 345",
            "PLSC 346",
            "PLSC 347",
            "PLSC 348",
            "PLSC 349",
            "PLSC 352",
            "PLSC 355C",
            "PLSC 359",
            "PLSC 360",
            "PLSC 362",
            "PLSC 365",
            "PLSC 366",
            "PLSC 368",
            "PLSC 374",
            "GLST 303"
          ]
        },
        {
          "name": "International Relations Subfield",
          "slots": 1,
          "credits_per_slot": 3,
          "eligible_courses": [
            "PLSC 204",
            "PLSC 213",
            "PLSC 252",
            "PLSC 300D",
            "PLSC 316",
            "PLSC 317",
            "PLSC 325",
            "PLSC 333",
            "PLSC 340",
            "PLSC 350",
            "PLSC 351",
            "PLSC 353",
            "PLSC 354",
            "PLSC 356",
            "PLSC 358",
            "PLSC 358D",
            "PLSC 363",
            "PLSC 364",
            "PLSC 367",
            "PLSC 369",
            "GLST 302"
          ]
        },
        {
          "name": "PLSC Electives",
          "description": "Four additional PLSC courses",
          "slots": 4,
          "credits_per_slot": 3,
          "eligible_courses": "ANY_PLSC_200_PLUS",
          "notes": "Any PLSC course 200+ not already used. PLSC 370 max 3cr toward major."
        }
      ]
    },
    {
      "code": "GLST-BA",
      "name": "Global Studies (BA)",
      "type": "major",
      "department": "GLST",
      "total_credits": 33,
      "unique_credits_required": 21,
      "double_dip_policy": "GLST_STRICT",
      "core_waivers": [
        "Societal/Cultural"
      ],
      "notes": [
        "Max 4 courses total can overlap between GLST and all other declared majors/minors.",
        "No more than 3 courses from any single department can count for GLST.",
        "Electives must include at least 2 courses from different world areas.",
        "Elective coursework must be from at least 3 departments.",
        "Language proficiency at 104-level required (does not count toward 33 credits).",
        "Portfolio submission required in final semester.",
        "Only 3 credits of GLST 370 count toward major."
      ],
      "categories": [
        {
          "name": "Core Requirements",
          "slots": 3,
          "credits_per_slot": 3,
          "eligible_courses_fixed": [
            {
              "course": "GLST 101",
              "required": true
            },
            {
              "course": "ANTH 100",
              "required": true
            },
            {
              "course": "PLSC 102",
              "required": true
            }
          ]
        },
        {
          "name": "300-Level GLST Courses",
          "description": "Select two of the following",
          "slots": 2,
          "credits_per_slot": 3,
          "eligible_courses": [
            "GLST 301",
            "GLST 302",
            "GLST 303",
            "GLST 304",
            "GLST 305",
            "GLST 306",
            "GLST 398"
          ]
        },
        {
          "name": "Internship",
          "slots": 1,
          "credits_per_slot": 3,
          "eligible_courses": [
            "GLST 370"
          ]
        },
        {
          "name": "GLST Electives",
          "description": "Six elective courses tagged with GLST interdisciplinary option",
          "slots": 6,
          "credits_per_slot": 3,
          "eligible_courses": "ANY_GLST_TAGGED",
          "constraints": {
            "min_world_areas": 2,
            "min_departments": 3,
            "max_from_single_dept": 3,
            "dept_cap_note": "The 3-per-dept cap counts ONLY electives. Required core courses (GLST 101, ANTH 100, PLSC 102) are excluded from this count."
          },
          "notes": "Must be from at least 2 world areas and 3 departments. A PLSC elective here does NOT consume a major-overlap slot unless it also counts toward the PLSC major."
        }
      ],
      "elective_pool_by_region": {
        "Africa": [
          "ANTH 213",
          "FNAR 355",
          "HIST 213",
          "HIST 342B",
          "HIST 342M",
          "HONR 210A",
          "HONR 210B",
          "HONR 210C",
          "LITR 219",
          "PLSC 340",
          "PLSC 342"
        ],
        "Asia": [
          "ANTH 215",
          "ASIA 101",
          "CHIN 341",
          "COMM 269",
          "COMM 301",
          "ENGL 292",
          "ENGL 315",
          "ENGL 315C",
          "FNAR 357",
          "FNAR 358",
          "FNAR 359",
          "HIST 208",
          "HIST 208Z",
          "HIST 343",
          "HIST 346B",
          "HIST 346C",
          "HIST 347A",
          "HIST 347C",
          "HIST 347D",
          "HIST 349A",
          "HIST 388A",
          "HONR 209B",
          "HONR 209C",
          "LITR 243",
          "LITR 244",
          "LITR 245",
          "LITR 287",
          "LITR 290",
          "LITR 292",
          "PHIL 192",
          "PHIL 193",
          "PHIL 335",
          "PLSC 345",
          "PLSC 346",
          "SOCL 251",
          "SOCL 263",
          "SOCL 266",
          "THEO 299",
          "THEO 352"
        ],
        "Europe": [
          "ANTH 222",
          "FREN 271",
          "FREN 309",
          "FREN 311",
          "FREN 390",
          "GERM 270",
          "GERM 271",
          "GERM 370",
          "HIST 267A",
          "HIST 267B",
          "HIST 322",
          "HIST 324",
          "HIST 325A",
          "HIST 326",
          "HIST 327A",
          "HIST 329C",
          "HIST 329N",
          "HIST 330",
          "HIST 330F",
          "HIST 331A",
          "HIST 334B",
          "HIST 335",
          "HIST 336",
          "HIST 337",
          "HIST 337A",
          "HIST 338A",
          "HIST 339C",
          "HIST 359C",
          "HONR 216A",
          "HONR 216B",
          "HONR 216C",
          "ITAL 271",
          "ITAL 284",
          "ITAL 319",
          "ITAL 320",
          "ITAL 390",
          "LITR 161",
          "LITR 200",
          "LITR 202",
          "LITR 203",
          "LITR 204",
          "LITR 221",
          "LITR 225",
          "LITR 230",
          "LITR 260",
          "LITR 262",
          "LITR 264",
          "LITR 267",
          "LITR 268",
          "LITR 268R",
          "LITR 283",
          "LITR 291",
          "PLSC 232",
          "PLSC 347",
          "PLSC 348",
          "PLSC 349",
          "PLSC 352",
          "PLSC 360",
          "PLSC 365",
          "ROST 382",
          "SOCL 267",
          "SPAN 271",
          "SPAN 311",
          "SPAN 321",
          "SPAN 331",
          "SPAN 341",
          "SPAN 349",
          "SPAN 362",
          "SPAN 363",
          "SPAN 366",
          "SPAN 390",
          "UNIV 301"
        ],
        "Latin America": [
          "ANTH 211",
          "ANTH 217",
          "ANTH 321",
          "ENGL 316C",
          "ENVS 340",
          "HIST 210",
          "HIST 278A",
          "HIST 353",
          "HIST 355",
          "HIST 356",
          "HIST 357",
          "HIST 358",
          "HONR 208A",
          "HONR 208B",
          "LASP 395",
          "LITR 211",
          "PLSC 343",
          "PLSC 344",
          "PLSC 351",
          "SPAN 271",
          "SPAN 363",
          "SPAN 370",
          "SPAN 380",
          "SPAN 381",
          "SPAN 385",
          "SPAN 389",
          "SPAN 390"
        ],
        "Middle East": [
          "ANTH 220",
          "HIST 209",
          "HIST 300",
          "HIST 341",
          "HIST 341B",
          "HONR 212B",
          "LITR 238",
          "PLSC 368",
          "PLSC 331"
        ]
      }
    },
    {
      "code": "PHIL-BA",
      "name": "Philosophy (BA)",
      "type": "major",
      "department": "PHIL",
      "total_credits": 33,
      "unique_credits_required": 21,
      "double_dip_policy": "CAS_DEFAULT",
      "core_waivers": ["Philosophical/Ethical"],
      "notes": [
        "At least 7 of 11 courses must be 300-level (8 if PHIL 301 taken instead of PHIL 274).",
        "At least 4 of 5 electives should be 300-level.",
        "All 300-level courses require 2 prior philosophy courses.",
        "Capstone seminars require 5 prior philosophy courses."
      ],
      "categories": [
        {
          "name": "Formal Logic",
          "description": "Select one",
          "slots": 1,
          "credits_per_slot": 3,
          "eligible_courses": [
            "PHIL 274",
            "PHIL 301"
          ]
        },
        {
          "name": "History of Philosophy",
          "description": "Both required",
          "slots": 2,
          "credits_per_slot": 3,
          "eligible_courses_fixed": [
            { "course": "PHIL 304", "required": true },
            { "course": "PHIL 309", "required": true }
          ]
        },
        {
          "name": "Ethics Distribution",
          "description": "Select one ethics course",
          "slots": 1,
          "credits_per_slot": 3,
          "eligible_courses": [
            "PHIL 181",
            "PHIL 182",
            "PHIL 283",
            "PHIL 284",
            "PHIL 285",
            "PHIL 286",
            "PHIL 287",
            "PHIL 288",
            "PHIL 289",
            "PHIL 321",
            "PHIL 322",
            "PHIL 324",
            "PHIL 324B",
            "PHIL 325",
            "PHIL 329",
            "PHIL 355",
            "PHIL 369",
            "PHIL 375",
            "PHIL 385",
            "PHIL 388"
          ]
        },
        {
          "name": "Metaphysics/Epistemology Distribution",
          "description": "Select one metaphysics or epistemology course",
          "slots": 1,
          "credits_per_slot": 3,
          "eligible_courses": [
            "PHIL 130",
            "PHIL 271",
            "PHIL 272",
            "PHIL 273",
            "PHIL 275",
            "PHIL 276",
            "PHIL 277",
            "PHIL 279",
            "PHIL 311",
            "PHIL 325",
            "PHIL 330",
            "PHIL 380",
            "PHIL 381",
            "PHIL 382",
            "PHIL 384",
            "PHIL 386",
            "PHIL 387",
            "PHIL 391",
            "PHIL 393"
          ]
        },
        {
          "name": "Capstone Seminar",
          "description": "Select one capstone seminar (requires 5 prior PHIL courses)",
          "slots": 1,
          "credits_per_slot": 3,
          "eligible_courses": [
            "PHIL 395",
            "PHIL 396",
            "PHIL 397",
            "PHIL 398",
            "PHIL 399"
          ]
        },
        {
          "name": "Philosophy Electives",
          "description": "Five additional PHIL courses",
          "slots": 5,
          "credits_per_slot": 3,
          "eligible_courses": "ANY_PHIL_ELECTIVE",
          "notes": "Any PHIL course not already used in another PHIL-BA category."
        }
      ]
    },
    {
      "code": "HIST-BA",
      "name": "History (BA)",
      "type": "major",
      "department": "HIST",
      "total_credits": 36,
      "unique_credits_required": 21,
      "double_dip_policy": "CAS_DEFAULT",
      "notes": [
        "Portfolio requirement: must submit a historiographical essay (typically from HIST 299) and a 300-level research paper.",
        "Minimum 6 courses must be completed at Loyola Chicago.",
        "Minimum 4 of the 300-level courses must be completed at Loyola Chicago.",
        "HIST 398 (Internship) may count as one elective."
      ],
      "categories": [
        {
          "name": "Introductory Courses — Tier 1",
          "description": "Select one foundational history course",
          "slots": 1,
          "credits_per_slot": 3,
          "eligible_courses": [
            "HIST 101",
            "HIST 102",
            "HIST 103",
            "HIST 104",
            "HONR 101",
            "HONR 102"
          ]
        },
        {
          "name": "Introductory Courses — Tier 2",
          "description": "Select one Tier 2 history course",
          "slots": 1,
          "credits_per_slot": 3,
          "eligible_courses": [
            "HIST 208",
            "HIST 208X",
            "HIST 208Z",
            "HIST 209",
            "HIST 210",
            "HIST 211",
            "HIST 212",
            "HIST 213",
            "HONR 203A",
            "HONR 203B",
            "HONR 203C",
            "HONR 208A",
            "HONR 208B",
            "HONR 208C",
            "HONR 209A",
            "HONR 209B",
            "HONR 209C",
            "HONR 210A",
            "HONR 210B",
            "HONR 210C",
            "HONR 212A",
            "HONR 212B",
            "HONR 212C"
          ]
        },
        {
          "name": "Methods",
          "description": "Select one methods course",
          "slots": 1,
          "credits_per_slot": 3,
          "eligible_courses": [
            "HIST 299",
            "INDS 380"
          ]
        },
        {
          "name": "Upper-Level Pre-Modern History",
          "description": "Select one upper-level pre-modern history course",
          "slots": 1,
          "credits_per_slot": 3,
          "eligible_courses": [
            "HIST 253A",
            "HIST 254A",
            "HIST 257A",
            "HIST 258A",
            "HIST 300B",
            "HIST 301",
            "HIST 303",
            "HIST 307",
            "HIST 308A",
            "HIST 308B",
            "HIST 308C",
            "HIST 308D",
            "HIST 309",
            "HIST 310",
            "HIST 310A",
            "HIST 310B",
            "HIST 310C",
            "HIST 310D",
            "HIST 310F",
            "HIST 310G",
            "HIST 310L",
            "HIST 311B",
            "HIST 312",
            "HIST 314",
            "HIST 314A",
            "HIST 315",
            "HIST 316",
            "HIST 317",
            "HIST 318A",
            "HIST 318B",
            "HIST 318C",
            "HIST 342A",
            "HIST 345A",
            "CLST 362",
            "THEO 317"
          ]
        },
        {
          "name": "Upper-Level Modern European History",
          "description": "Select one upper-level modern European history course",
          "slots": 1,
          "credits_per_slot": 3,
          "eligible_courses": [
            "HIST 265A",
            "HIST 267A",
            "HIST 267B",
            "HIST 300C",
            "HIST 320",
            "HIST 321",
            "HIST 322",
            "HIST 324",
            "HIST 325",
            "HIST 325A",
            "HIST 326",
            "HIST 327A",
            "HIST 328",
            "HIST 328A",
            "HIST 329",
            "HIST 329C",
            "HIST 329N",
            "HIST 330",
            "HIST 330F",
            "HIST 331A",
            "HIST 334A",
            "HIST 334B",
            "HIST 335",
            "HIST 336",
            "HIST 337",
            "HIST 337A",
            "HIST 338A",
            "HIST 338B",
            "HIST 339C",
            "HIST 339F",
            "THEO 318"
          ]
        },
        {
          "name": "Upper-Level U.S. History",
          "description": "Select one upper-level U.S. history course",
          "slots": 1,
          "credits_per_slot": 3,
          "eligible_courses": [
            "HIST 280A",
            "HIST 290A",
            "HIST 291A",
            "HIST 297E",
            "HIST 298A",
            "HIST 300D",
            "HIST 360",
            "HIST 360A",
            "HIST 361",
            "HIST 362",
            "HIST 363",
            "HIST 366A",
            "HIST 367",
            "HIST 369",
            "HIST 370",
            "HIST 372",
            "HIST 373",
            "HIST 373A",
            "HIST 374",
            "HIST 375",
            "HIST 376",
            "HIST 376A",
            "HIST 377",
            "HIST 378",
            "HIST 379A",
            "HIST 379B",
            "HIST 380",
            "HIST 380A",
            "HIST 381",
            "HIST 382",
            "HIST 384",
            "HIST 385",
            "HIST 386",
            "HIST 388",
            "HIST 388A",
            "HIST 389B",
            "HIST 389C",
            "HIST 389F",
            "HIST 389K",
            "HIST 389N",
            "HIST 389W",
            "ECON 327"
          ]
        },
        {
          "name": "Upper-Level World History",
          "description": "Select one upper-level world history course",
          "slots": 1,
          "credits_per_slot": 3,
          "eligible_courses": [
            "HIST 275A",
            "HIST 278A",
            "HIST 279C",
            "HIST 279E",
            "HIST 300E",
            "HIST 340B",
            "HIST 341",
            "HIST 341B",
            "HIST 341C",
            "HIST 342B",
            "HIST 342C",
            "HIST 342D",
            "HIST 342M",
            "HIST 343",
            "HIST 346A",
            "HIST 346B",
            "HIST 346C",
            "HIST 347A",
            "HIST 347C",
            "HIST 347D",
            "HIST 349",
            "HIST 349A",
            "HIST 350",
            "HIST 351",
            "HIST 352",
            "HIST 353",
            "HIST 355",
            "HIST 356",
            "HIST 357",
            "HIST 358",
            "HIST 359",
            "HIST 359C",
            "HIST 359D",
            "HIST 359E",
            "HIST 359F",
            "HIST 359H"
          ]
        },
        {
          "name": "History Electives",
          "description": "Five additional history courses not used elsewhere",
          "slots": 5,
          "credits_per_slot": 3,
          "eligible_courses": "ANY_HIST_ELECTIVE",
          "notes": "Any HIST course not already used in another HIST-BA category. HIST 398 (Internship) may count as one elective."
        }
      ]
    },
    {
      "code": "ENGL-BA",
      "name": "English (BA)",
      "type": "major",
      "department": "ENGL",
      "total_credits": 36,
      "unique_credits_required": 21,
      "double_dip_policy": "CAS_DEFAULT",
      "notes": [
        "Nine of twelve courses (27 hours) must be at the 300-level.",
        "ENGL 274 (Exploring Shakespeare) does NOT fulfill the Shakespeare requirement.",
        "At least one course must be designated by the department as 'multicultural'.",
        "Up to three elective courses (9 hours) may be drawn from UCLR 100E and advanced 200-level (ENGL 270+) courses."
      ],
      "categories": [
        {
          "name": "Literary Theory",
          "description": "Select one",
          "slots": 1,
          "credits_per_slot": 3,
          "eligible_courses": [
            "ENGL 354",
            "ENGL 355"
          ]
        },
        {
          "name": "Shakespeare",
          "description": "Select one",
          "slots": 1,
          "credits_per_slot": 3,
          "eligible_courses": [
            "ENGL 326",
            "ENGL 327"
          ],
          "notes": "ENGL 274 does NOT fulfill this requirement."
        },
        {
          "name": "Capstone",
          "description": "Advanced Seminar",
          "slots": 1,
          "credits_per_slot": 3,
          "eligible_courses_fixed": [
            { "course": "ENGL 390", "required": true }
          ]
        },
        {
          "name": "English Literature Before 1700",
          "description": "At least one course from the pre-1700 period",
          "slots": 1,
          "credits_per_slot": 3,
          "eligible_courses": [
            "ENGL 306A",
            "ENGL 312A",
            "ENGL 313A",
            "ENGL 320",
            "ENGL 321",
            "ENGL 322",
            "ENGL 323",
            "ENGL 325",
            "ENGL 328",
            "ENGL 329",
            "ENGL 359A",
            "ENGL 362A",
            "ENGL 363A",
            "ENGL 368A",
            "ENGL 369A",
            "ENGL 372A",
            "ENGL 379A",
            "ENGL 381A",
            "ENGL 382A"
          ]
        },
        {
          "name": "English Literature 1700-1900",
          "description": "At least one course from the 1700-1900 period",
          "slots": 1,
          "credits_per_slot": 3,
          "eligible_courses": [
            "ENGL 306B",
            "ENGL 312B",
            "ENGL 313B",
            "ENGL 335",
            "ENGL 338",
            "ENGL 340",
            "ENGL 343",
            "ENGL 359B",
            "ENGL 362B",
            "ENGL 368B",
            "ENGL 369B",
            "ENGL 372B",
            "ENGL 375",
            "ENGL 376",
            "ENGL 379B",
            "ENGL 381B",
            "ENGL 382B",
            "ENGL 384B"
          ]
        },
        {
          "name": "English Literature Before 1900 (Additional)",
          "description": "One additional course from either pre-1700 or 1700-1900",
          "slots": 1,
          "credits_per_slot": 3,
          "eligible_courses": [
            "ENGL 306A",
            "ENGL 312A",
            "ENGL 313A",
            "ENGL 320",
            "ENGL 321",
            "ENGL 322",
            "ENGL 323",
            "ENGL 325",
            "ENGL 328",
            "ENGL 329",
            "ENGL 359A",
            "ENGL 362A",
            "ENGL 363A",
            "ENGL 368A",
            "ENGL 369A",
            "ENGL 372A",
            "ENGL 379A",
            "ENGL 381A",
            "ENGL 382A",
            "ENGL 306B",
            "ENGL 312B",
            "ENGL 313B",
            "ENGL 335",
            "ENGL 338",
            "ENGL 340",
            "ENGL 343",
            "ENGL 359B",
            "ENGL 362B",
            "ENGL 368B",
            "ENGL 369B",
            "ENGL 372B",
            "ENGL 375",
            "ENGL 376",
            "ENGL 379B",
            "ENGL 381B",
            "ENGL 382B",
            "ENGL 384B"
          ]
        },
        {
          "name": "English Literature Since 1900",
          "description": "Select one course from the post-1900 period",
          "slots": 1,
          "credits_per_slot": 3,
          "eligible_courses": [
            "ENGL 306C",
            "ENGL 311",
            "ENGL 312C",
            "ENGL 313C",
            "ENGL 315C",
            "ENGL 316C",
            "ENGL 344",
            "ENGL 345",
            "ENGL 348",
            "ENGL 351",
            "ENGL 359C",
            "ENGL 361",
            "ENGL 362C",
            "ENGL 363C",
            "ENGL 367",
            "ENGL 368C",
            "ENGL 371",
            "ENGL 372C",
            "ENGL 377",
            "ENGL 379C",
            "ENGL 381C",
            "ENGL 382C",
            "ENGL 384C"
          ]
        },
        {
          "name": "ENGL Electives",
          "description": "Five additional ENGL elective courses",
          "slots": 5,
          "credits_per_slot": 3,
          "eligible_courses": "ANY_ENGL_ELECTIVE",
          "notes": "Up to three electives may be drawn from UCLR 100E and advanced 200-level (ENGL 270+) courses. Remaining must be 300-level ENGL."
        }
      ]
    },
    {
      "code": "SPAN-BA",
      "name": "Spanish (BA)",
      "type": "major",
      "department": "SPAN",
      "total_credits": 30,
      "unique_credits_required": 21,
      "double_dip_policy": "CAS_DEFAULT",
      "notes": [
        "Students must complete either the non-heritage sequence (SPAN 250 + SPAN 251) or the native-speaker sequence (SPAN 252 + SPAN 253).",
        "Six 300-level courses required; at least one must focus exclusively on Latin America and one exclusively on Spain.",
        "Completion and presentation of an e-portfolio with brief personal statement in Spanish required (no credit hours).",
        "SPAN 395 (Internship) counts as a 300-level elective."
      ],
      "categories": [
        {
          "name": "Composition & Conversation",
          "description": "Two courses from either the non-heritage or native-speaker sequence",
          "slots": 2,
          "credits_per_slot": 3,
          "eligible_courses": [
            "SPAN 250",
            "SPAN 251",
            "SPAN 252",
            "SPAN 253"
          ],
          "notes": "Non-heritage track: SPAN 250 + 251. Native-speaker track: SPAN 252 + 253. Complete one sequence."
        },
        {
          "name": "Introduction to Critical Analysis",
          "description": "Required gateway course",
          "slots": 1,
          "credits_per_slot": 3,
          "eligible_courses_fixed": [
            { "course": "SPAN 270", "required": true }
          ]
        },
        {
          "name": "Introduction to Literature & Culture",
          "description": "Select one introductory literature course",
          "slots": 1,
          "credits_per_slot": 3,
          "eligible_courses": [
            "SPAN 271",
            "SPAN 272"
          ],
          "notes": "SPAN 271 focuses on Iberian literature; SPAN 272 focuses on Spanish American literature."
        },
        {
          "name": "Advanced Electives (300-Level)",
          "description": "Six 300-level SPAN courses; at least one on Latin America, one on Spain",
          "slots": 6,
          "credits_per_slot": 3,
          "eligible_courses": [
            "SPAN 300",
            "SPAN 302",
            "SPAN 305",
            "SPAN 308",
            "SPAN 311",
            "SPAN 314",
            "SPAN 319",
            "SPAN 321",
            "SPAN 326",
            "SPAN 330",
            "SPAN 331",
            "SPAN 336",
            "SPAN 339",
            "SPAN 340",
            "SPAN 341",
            "SPAN 346",
            "SPAN 347",
            "SPAN 349",
            "SPAN 352",
            "SPAN 353",
            "SPAN 360",
            "SPAN 361",
            "SPAN 362",
            "SPAN 363",
            "SPAN 364",
            "SPAN 365",
            "SPAN 366",
            "SPAN 367",
            "SPAN 368",
            "SPAN 370",
            "SPAN 371",
            "SPAN 380",
            "SPAN 381",
            "SPAN 382",
            "SPAN 385",
            "SPAN 389",
            "SPAN 390",
            "SPAN 391",
            "SPAN 395",
            "SPAN 396",
            "SPAN 397"
          ],
          "notes": "At least one must focus on Latin America and one on Spain."
        }
      ]
    },
    {
      "code": "THEO-BA",
      "name": "Theology (BA)",
      "type": "major",
      "department": "THEO",
      "total_credits": 36,
      "unique_credits_required": 21,
      "double_dip_policy": "CAS_DEFAULT",
      "notes": [
        "Minimum 18 credit hours must be completed at Loyola.",
        "At least 5 of 12 courses must be at the 300-level or higher.",
        "With prior approval, up to two 200-level or above elective courses may be taken outside the Department of Theology.",
        "THEO 280 must be taken as an Engaged Learning course when used for capstone."
      ],
      "categories": [
        {
          "name": "Doctrine Course",
          "description": "Select one doctrine course",
          "slots": 1,
          "credits_per_slot": 3,
          "eligible_courses": [
            "THEO 100",
            "THEO 265",
            "THEO 266",
            "THEO 267"
          ]
        },
        {
          "name": "Hebrew Bible/Old Testament",
          "description": "Select one Hebrew Bible/Old Testament course",
          "slots": 1,
          "credits_per_slot": 3,
          "eligible_courses": [
            "THEO 231",
            "THEO 302",
            "THEO 303",
            "THEO 304"
          ]
        },
        {
          "name": "New Testament",
          "description": "Select one New Testament course",
          "slots": 1,
          "credits_per_slot": 3,
          "eligible_courses": [
            "THEO 232",
            "THEO 311",
            "THEO 313"
          ]
        },
        {
          "name": "Christian Thought",
          "description": "Select one Christian Thought course",
          "slots": 1,
          "credits_per_slot": 3,
          "eligible_courses": [
            "THEO 317",
            "THEO 318"
          ]
        },
        {
          "name": "Non-Christian Religious Tradition",
          "description": "Select one course on a non-Christian religious tradition",
          "slots": 1,
          "credits_per_slot": 3,
          "eligible_courses": [
            "THEO 107",
            "THEO 272",
            "THEO 282",
            "THEO 295",
            "THEO 297",
            "THEO 299",
            "THEO 350",
            "THEO 352",
            "THEO 353",
            "THEO 356",
            "THEO 365",
            "THEO 366"
          ]
        },
        {
          "name": "Ethics",
          "description": "Select one ethics course",
          "slots": 1,
          "credits_per_slot": 3,
          "eligible_courses": [
            "THEO 185",
            "THEO 186",
            "THEO 203",
            "THEO 204",
            "THEO 293",
            "THEO 340",
            "THEO 342",
            "THEO 343",
            "THEO 344"
          ]
        },
        {
          "name": "Theology Capstone",
          "description": "Select one capstone course",
          "slots": 1,
          "credits_per_slot": 3,
          "eligible_courses": [
            "THEO 373",
            "THEO 280",
            "THEO 353"
          ],
          "notes": "THEO 353 requires prior approval. THEO 280 must be taken as Engaged Learning."
        },
        {
          "name": "Theology Electives",
          "description": "Five additional THEO courses at 200-level or above",
          "slots": 5,
          "credits_per_slot": 3,
          "eligible_courses": "ANY_THEO_ELECTIVE",
          "notes": "Any THEO course 200+ not already used. With approval, up to two electives may be outside Theology."
        }
      ]
    },
    {
      "code": "ANTH-BA",
      "name": "Anthropology (BA)",
      "type": "major",
      "department": "ANTH",
      "total_credits": 36,
      "unique_credits_required": 21,
      "double_dip_policy": "CAS_DEFAULT",
      "notes": [
        "At least 18 credit hours must be completed at Loyola.",
        "Students contemplating graduate studies should select ANTH 304 Anthropological Theory.",
        "ANTH 396, 397, 398, and 399 may be taken more than once, but only one may count toward the major."
      ],
      "categories": [
        {
          "name": "Required Foundations",
          "description": "ANTH 101 and ANTH 231 required",
          "slots": 2,
          "credits_per_slot": 3,
          "eligible_courses_fixed": [
            { "course": "ANTH 101", "required": true },
            { "course": "ANTH 231", "required": true }
          ]
        },
        {
          "name": "Introductory Course",
          "description": "Select one of ANTH 100 or ANTH 102",
          "slots": 1,
          "credits_per_slot": 3,
          "eligible_courses": [
            "ANTH 100",
            "ANTH 102"
          ],
          "notes": "The unchosen course can count as an elective."
        },
        {
          "name": "Ethnographic Requirement",
          "description": "Choose two ethnographic courses",
          "slots": 2,
          "credits_per_slot": 3,
          "eligible_courses": [
            "ANTH 207",
            "ANTH 208",
            "ANTH 211",
            "ANTH 212",
            "ANTH 213",
            "ANTH 214",
            "ANTH 215",
            "ANTH 216",
            "ANTH 217",
            "ANTH 220",
            "ANTH 222",
            "ANTH 224",
            "ANTH 225"
          ]
        },
        {
          "name": "Theoretical Requirement",
          "description": "Choose two theoretical courses",
          "slots": 2,
          "credits_per_slot": 3,
          "eligible_courses": [
            "ANTH 303",
            "ANTH 304",
            "ANTH 305",
            "ANTH 306",
            "ANTH 307",
            "ANTH 309",
            "ANTH 314",
            "ANTH 316",
            "ANTH 317",
            "ANTH 319",
            "ANTH 321",
            "ANTH 330",
            "ANTH 332",
            "ANTH 348",
            "ANTH 361",
            "ANTH 363"
          ]
        },
        {
          "name": "Archaeology Requirement",
          "description": "Choose one archaeology course",
          "slots": 1,
          "credits_per_slot": 3,
          "eligible_courses": [
            "ANTH 241",
            "ANTH 242",
            "ANTH 243",
            "ANTH 244",
            "ANTH 245",
            "ANTH 246",
            "ANTH 247"
          ]
        },
        {
          "name": "Bio-Anthropology Requirement",
          "description": "Choose one biological anthropology course",
          "slots": 1,
          "credits_per_slot": 3,
          "eligible_courses": [
            "ANTH 324",
            "ANTH 325",
            "ANTH 326",
            "ANTH 327"
          ]
        },
        {
          "name": "Anthropology Electives",
          "description": "Three additional ANTH electives",
          "slots": 3,
          "credits_per_slot": 3,
          "eligible_courses": "ANY_ANTH_ELECTIVE",
          "notes": "One elective may be 100-level; two must be 200+. Only one of ANTH 396/397/398/399 may count."
        }
      ]
    },
    {
      "code": "FNAR-BA",
      "name": "Fine Arts (BA)",
      "type": "major",
      "department": "FNAR",
      "total_credits": 45,
      "unique_credits_required": 21,
      "double_dip_policy": "CAS_DEFAULT",
      "notes": [
        "LUC catalogs Fine Arts as four separate BA concentrations: Drawing/Painting/Printmaking (45cr), Photography/Video Art (45cr), Sculpture/Ceramics (42cr), and Visual Communication (45cr).",
        "This definition models the shared structure of the three studio art concentrations (DPP, PVA, SC).",
        "Sculpture/Ceramics is 42 total credits (7 applied courses instead of 8).",
        "All concentrations require FNAR 115 (Foundations of Photography)."
      ],
      "categories": [
        {
          "name": "Foundation Courses",
          "description": "Required introductory studio courses",
          "slots": 2,
          "credits_per_slot": 3,
          "eligible_courses_fixed": [
            { "course": "FNAR 110", "required": true },
            { "course": "FNAR 113", "required": true }
          ]
        },
        {
          "name": "Art History",
          "description": "Two art history courses (specific requirements vary by concentration)",
          "slots": 2,
          "credits_per_slot": 3,
          "eligible_courses": [
            "FNAR 200",
            "FNAR 201",
            "FNAR 202",
            "FNAR 306",
            "FNAR 365"
          ],
          "notes": "DPP requires FNAR 201 + 202. PVA requires FNAR 365 + one of 202/306. SC requires one of 200/201 + 202."
        },
        {
          "name": "Applied Courses",
          "description": "Studio courses including Foundations of Photography plus concentration-specific work",
          "slots": 8,
          "credits_per_slot": 3,
          "eligible_courses": [
            "FNAR 114",
            "FNAR 115",
            "FNAR 118",
            "FNAR 120",
            "FNAR 121",
            "FNAR 124",
            "FNAR 132",
            "FNAR 190",
            "FNAR 213",
            "FNAR 214",
            "FNAR 216",
            "FNAR 219",
            "FNAR 222",
            "FNAR 233",
            "FNAR 311",
            "FNAR 315",
            "FNAR 320",
            "FNAR 322"
          ],
          "notes": "FNAR 115 required in all concentrations. SC has 7 applied courses (42cr total) instead of 8."
        },
        {
          "name": "Synthesis Courses",
          "description": "Critical approaches and capstone",
          "slots": 2,
          "credits_per_slot": 3,
          "eligible_courses_fixed": [
            { "course": "FNAR 388", "required": true },
            { "course": "FNAR 398", "required": true }
          ]
        },
        {
          "name": "FNAR Electives",
          "description": "One additional FNAR elective course",
          "slots": 1,
          "credits_per_slot": 3,
          "eligible_courses": [
            "FNAR 114",
            "FNAR 118",
            "FNAR 120",
            "FNAR 121",
            "FNAR 123",
            "FNAR 124",
            "FNAR 132",
            "FNAR 190",
            "FNAR 202",
            "FNAR 213",
            "FNAR 218",
            "FNAR 233",
            "FNAR 306",
            "FNAR 368"
          ],
          "notes": "Courses already counted in another category cannot be reused."
        }
      ]
    },
    {
      "code": "CORE",
      "name": "University Core Curriculum",
      "type": "core",
      "total_credits": 48,
      "notes": [
        "16 required courses across 10 Core Areas.",
        "Some areas waived by declaring certain majors/minors.",
        "All Core classes must be taken at Loyola.",
        "6 areas require 2 courses (Foundational + Tier 2), 4 areas require 1 course."
      ],
      "categories": [
        {
          "name": "Artistic Knowledge and Inquiry",
          "slots": 1,
          "credits_per_slot": 3,
          "tier_structure": "single"
        },
        {
          "name": "College Writing Seminar",
          "slots": 1,
          "credits_per_slot": 3,
          "tier_structure": "single",
          "eligible_courses": [
            "UCWR 110"
          ]
        },
        {
          "name": "Ethical Knowledge and Inquiry",
          "slots": 1,
          "credits_per_slot": 3,
          "tier_structure": "single"
        },
        {
          "name": "Quantitative Knowledge and Inquiry",
          "slots": 1,
          "credits_per_slot": 3,
          "tier_structure": "single"
        },
        {
          "name": "Historical Knowledge and Inquiry",
          "slots": 2,
          "credits_per_slot": 3,
          "tier_structure": "foundation_plus_tier2",
          "notes": "Tier 1 (Foundational) + Tier 2"
        },
        {
          "name": "Literary Knowledge and Inquiry",
          "slots": 2,
          "credits_per_slot": 3,
          "tier_structure": "foundation_plus_tier2"
        },
        {
          "name": "Philosophical Knowledge and Inquiry",
          "slots": 2,
          "credits_per_slot": 3,
          "tier_structure": "foundation_plus_tier2"
        },
        {
          "name": "Scientific Knowledge and Inquiry",
          "slots": 2,
          "credits_per_slot": 3,
          "tier_structure": "foundation_plus_tier2"
        },
        {
          "name": "Societal and Cultural Knowledge and Inquiry",
          "slots": 2,
          "credits_per_slot": 3,
          "tier_structure": "foundation_plus_tier2"
        },
        {
          "name": "Theological and Religious Knowledge and Inquiry",
          "slots": 2,
          "credits_per_slot": 3,
          "tier_structure": "foundation_plus_tier2"
        }
      ]
    },
    {
      "code": "CAS-GRAD",
      "name": "College of Arts & Sciences Graduation Requirements",
      "type": "college",
      "notes": [
        "120 total credit hours required for graduation.",
        "Minimum 2.00 cumulative GPA.",
        "Minimum 2.00 GPA in Core Curriculum.",
        "Final 45 hours must be at Loyola.",
        "UNIV 101 required.",
        "At least 1 Engaged Learning course required."
      ],
      "categories": [
        {
          "name": "Writing Intensive",
          "slots": 2,
          "credits_per_slot": 3,
          "notes": "Two Writing Intensive courses required (6 credit hours)"
        },
        {
          "name": "Foreign Language",
          "slots": 1,
          "credits_per_slot": 3,
          "notes": "Language at 102-level or higher, or language competency test"
        },
        {
          "name": "Engaged Learning",
          "slots": 1,
          "credits_per_slot": 3,
          "notes": "At least one Engaged Learning course"
        },
        {
          "name": "UNIV 101",
          "slots": 1,
          "credits_per_slot": 1,
          "eligible_courses": [
            "UNIV 101"
          ]
        }
      ]
    },
    {
      "code": "SPAN-LANG",
      "name": "Spanish Language Requirement (for GLST + CAS)",
      "type": "requirement",
      "notes": [
        "CAS requires foreign language at 102-level or higher.",
        "GLST requires foreign language proficiency at 104-level.",
        "GLST language courses do NOT count toward the 33 GLST credit hours.",
        "These courses DO count toward the 120 total graduation credits."
      ],
      "categories": [
        {
          "name": "Spanish Sequence",
          "slots": 3,
          "credits_per_slot": 3,
          "eligible_courses": [
            "SPAN 102",
            "SPAN 103",
            "SPAN 104"
          ],
          "notes": "SPAN 102 satisfies CAS requirement; SPAN 104 satisfies GLST requirement"
        }
      ]
    }
  ],
  "overlap_rules": {
    "cas_default": {
      "description": "College of Arts & Sciences Double Dipping Policy",
      "major_unique_credits": 21,
      "minor_unique_credits": 8,
      "notes": "Departments may enforce stricter policies."
    },
    "pairs": [
      {
        "programs": [
          "PLSC-BA",
          "GLST-BA"
        ],
        "max_shared_courses": 4,
        "constraint_source": "GLST",
        "notes": [
          "GLST is the binding constraint. PLSC uses CAS default (21 unique).",
          "The 3-from-single-dept cap applies to GLST ELECTIVES only, not required core courses.",
          "PLSC 102 is a required GLST core course and does NOT count against the 3-PLSC-elective cap.",
          "A PLSC course used as a GLST elective only burns an overlap slot if it ALSO counts toward the PLSC major.",
          "A PLSC elective in GLST that is NOT fulfilling a PLSC major requirement = no overlap consumed."
        ]
      },
      {
        "programs": [
          "PLSC-BA",
          "CORE"
        ],
        "overlap_type": "waiver",
        "details": "PLSC BA waives Core Societal/Cultural Knowledge (both tiers = 6 credits). Core courses with PLSC Knowledge Area tags can satisfy both Core and contribute to major understanding, but the PLSC credit hours still count toward the PLSC 33.",
        "notes": "This is a WAIVER not double-counting. Student does not need separate Societal/Cultural courses."
      },
      {
        "programs": [
          "GLST-BA",
          "CORE"
        ],
        "overlap_type": "waiver",
        "details": "GLST BA waives Core Societal/Cultural Knowledge (both tiers = 6 credits).",
        "notes": "Same waiver as PLSC. Student with both majors benefits once (not twice)."
      }
    ]
  },
  "core_waivers_by_program": {
    "PLSC-BA": [
      "Societal and Cultural Knowledge and Inquiry"
    ],
    "GLST-BA": [
      "Societal and Cultural Knowledge and Inquiry"
    ],
    "HIST-BA": [
      "Historical Knowledge and Inquiry"
    ],
    "ENGL-BA": [
      "Literary Knowledge and Inquiry"
    ],
    "PHIL-BA": [
      "Philosophical Knowledge and Inquiry",
      "Ethical Knowledge and Inquiry"
    ],
    "SPAN-BA": [
      "Literary Knowledge and Inquiry"
    ],
    "THEO-BA": [
      "Theological and Religious Knowledge and Inquiry"
    ],
    "ANTH-BA": [
      "Scientific Knowledge and Inquiry",
      "Societal and Cultural Knowledge and Inquiry"
    ],
    "FNAR-BA": [
      "Artistic Knowledge and Inquiry"
    ]
  }
}